print_partial_datasets/__init__.py
print_partial_datasets/cli.py
print_partial_datasets/filetreemanager.py
print_partial_datasets-0.2.3.dist-info/AUTHORS.rst
print_partial_datasets-0.2.3.dist-info/LICENSE
print_partial_datasets-0.2.3.dist-info/METADATA
print_partial_datasets-0.2.3.dist-info/WHEEL
print_partial_datasets-0.2.3.dist-info/entry_points.txt
print_partial_datasets-0.2.3.dist-info/top_level.txt
print_partial_datasets-0.2.3.dist-info/RECORD
