Metadata-Version: 2.1
Name: print-partial-datasets
Version: 0.2.3
Summary: Print partial datasets.
Home-page: https://github.com/Craskermasker/print_partial_datasets
Author: Evan C Edmond
Author-email: eedmond@gmail.com
License: Apache Software License 2.0
Keywords: print_partial_datasets
Platform: UNKNOWN
Classifier: Development Status :: 2 - Pre-Alpha
Classifier: Intended Audience :: Developers
Classifier: License :: OSI Approved :: Apache Software License
Classifier: Natural Language :: English
Classifier: Programming Language :: Python :: 3
Classifier: Programming Language :: Python :: 3.5
Classifier: Programming Language :: Python :: 3.6
Classifier: Programming Language :: Python :: 3.7
Classifier: Programming Language :: Python :: 3.8
Requires-Python: >=3.5
Requires-Dist: fslpy
